MANIFEST.in
README.md
setup.py
./src/aggregate.cpp
./src/alias.cpp
./src/atom.cpp
./src/base.cpp
./src/bitvec.cpp
./src/bond.cpp
./src/bondtyper.cpp
./src/builder.cpp
./src/canon.cpp
./src/chains.cpp
./src/chargemodel.cpp
./src/chiral.cpp
./src/conformersearch.cpp
./src/confsearch.cpp
./src/data.cpp
./src/data_utilities.cpp
./src/descriptor.cpp
./src/distgeom.cpp
./src/doxygen_pages.cpp
./src/fingerprint.cpp
./src/forcefield.cpp
./src/format.cpp
./src/generic.cpp
./src/graphsym.cpp
./src/grid.cpp
./src/griddata.cpp
./src/isomorphism.cpp
./src/kekulize.cpp
./src/locale.cpp
./src/matrix.cpp
./src/mcdlutil.cpp
./src/memcpy.c
./src/mol.cpp
./src/molchrg.cpp
./src/obconversion.cpp
./src/oberror.cpp
./src/obiter.cpp
./src/obmolecformat.cpp
./src/obutil.cpp
./src/op.cpp
./src/parsmart.cpp
./src/patty.cpp
./src/phmodel.cpp
./src/plugin.cpp
./src/pointgroup.cpp
./src/query.cpp
./src/rand.cpp
./src/residue.cpp
./src/ring.cpp
./src/rotamer.cpp
./src/rotor.cpp
./src/spectrophore.cpp
./src/strncasecmp.c
./src/tautomer.cpp
./src/tokenst.cpp
./src/transform.cpp
./src/typer.cpp
./src/charges/eem.cpp
./src/charges/eqeq.cpp
./src/charges/fromfile.cpp
./src/charges/gasteiger.cpp
./src/charges/mmff94.cpp
./src/charges/none.cpp
./src/charges/qeq.cpp
./src/charges/qtpie.cpp
./src/depict/asciipainter.cpp
./src/depict/commandpainter.cpp
./src/depict/depict.cpp
./src/depict/svgpainter.cpp
./src/descriptors/cansmidescriptor.cpp
./src/descriptors/cmpdfilter.cpp
./src/descriptors/filters.cpp
./src/descriptors/groupcontrib.cpp
./src/descriptors/smartsdescriptors.cpp
./src/fingerprints/finger2.cpp
./src/fingerprints/finger3.cpp
./src/fingerprints/fingerecfp.cpp
./src/forcefields/forcefieldgaff.cpp
./src/forcefields/forcefieldghemical.cpp
./src/forcefields/forcefieldmm2.cpp
./src/forcefields/forcefieldmmff94.cpp
./src/forcefields/forcefielduff.cpp
./src/formats/APIInterface.cpp
./src/formats/ArrayList.c
./src/formats/CSRformat.cpp
./src/formats/MCDLformat.cpp
./src/formats/MNAformat.cpp
maagbel.egg-info/PKG-INFO
maagbel.egg-info/SOURCES.txt
maagbel.egg-info/dependency_links.txt
maagbel.egg-info/top_level.txt
