Metadata-Version: 2.1
Name: maagbel
Version: 0.1.1
Summary: Reduced fork of OpenBabel for the ManipulateAggregates tools
Home-page: https://github.com/razziel89/MaAg-bel
Author: Torsten Sachse
License: UNKNOWN
Platform: UNKNOWN
Classifier: Development Status :: 4 - Beta
Classifier: Intended Audience :: Developers
Classifier: Intended Audience :: Science/Research
Classifier: License :: OSI Approved :: GNU General Public License v2 (GPLv2)
Classifier: Natural Language :: English
Classifier: Operating System :: POSIX :: Linux
Classifier: Programming Language :: C++
Classifier: Programming Language :: Python :: 3.8
Classifier: Programming Language :: Python :: 3 :: Only
